README.md
setup.py
text2art/__init__.py
text2art/color.py
text2art/main.py
text2art/utils.py
text2art.egg-info/PKG-INFO
text2art.egg-info/SOURCES.txt
text2art.egg-info/dependency_links.txt
text2art.egg-info/entry_points.txt
text2art.egg-info/requires.txt
text2art.egg-info/top_level.txt