Metadata-Version: 1.0
Name: text2art
Version: 0.1.6
Summary: Generating controlled terminal art fonts
Home-page: https://github.com/Fenghuapiao/text2art
Author: hangfengYang
Author-email: yhf5fhy@gmail.com
License: MIT
Platform: UNKNOWN
